livekit/plugins/vozy/__init__.py
livekit/plugins/vozy/cliente_websocket.py
livekit/plugins/vozy/log.py
livekit/plugins/vozy/models.py
livekit/plugins/vozy/tts.py
livekit/plugins/vozy/tts2.py
livekit/plugins/vozy/tts3.py
livekit/plugins/vozy/tts4.py
livekit/plugins/vozy/tts5.py
livekit/plugins/vozy/version.py
livekit_plugins_vozy-0.1.0.dist-info/METADATA
livekit_plugins_vozy-0.1.0.dist-info/WHEEL
livekit_plugins_vozy-0.1.0.dist-info/top_level.txt
livekit_plugins_vozy-0.1.0.dist-info/RECORD
